MANIFEST.in
README.txt
setup.cfg
setup.py
docs/HISTORY.txt
docs/HISTORY.txt~
docs/INSTALL.txt
docs/LICENSE.GPL
docs/LICENSE.txt
ityou/__init__.py
ityou.bluetheme.egg-info/PKG-INFO
ityou.bluetheme.egg-info/SOURCES.txt
ityou.bluetheme.egg-info/dependency_links.txt
ityou.bluetheme.egg-info/entry_points.txt
ityou.bluetheme.egg-info/namespace_packages.txt
ityou.bluetheme.egg-info/not-zip-safe
ityou.bluetheme.egg-info/paster_plugins.txt
ityou.bluetheme.egg-info/requires.txt
ityou.bluetheme.egg-info/top_level.txt
ityou/bluetheme/__init__.py
ityou/bluetheme/configure.zcml
ityou/bluetheme/profiles.zcml
ityou/bluetheme/setuphandlers.py
ityou/bluetheme/skins.zcml
ityou/bluetheme/tests.py
ityou/bluetheme/version.txt
ityou/bluetheme/Extensions/install.py
ityou/bluetheme/browser/__init__.py
ityou/bluetheme/browser/common.py
ityou/bluetheme/browser/configure.zcml
ityou/bluetheme/browser/event_listing.py
ityou/bluetheme/browser/interfaces.py
ityou/bluetheme/browser/viewlet.pt
ityou/bluetheme/browser/viewlets.py
ityou/bluetheme/browser/images/README.txt
ityou/bluetheme/browser/images/bg.png
ityou/bluetheme/browser/images/searchField.png
ityou/bluetheme/browser/images/tab_Members.png
ityou/bluetheme/browser/images/tab_Members_hi.png
ityou/bluetheme/browser/images/tab_xxx.png
ityou/bluetheme/browser/images/tab_xxx_hi.png
ityou/bluetheme/browser/javascripts/README.txt
ityou/bluetheme/browser/javascripts/bluetheme-jq.js
ityou/bluetheme/browser/stylesheets/README.txt
ityou/bluetheme/browser/stylesheets/main.css
ityou/bluetheme/browser/stylesheets/tabs.css
ityou/bluetheme/browser/templates/event_listing.pt
ityou/bluetheme/browser/templates/path_bar.pt
ityou/bluetheme/browser/templates/searchbox.pt
ityou/bluetheme/locales/README.txt
ityou/bluetheme/profiles/default/cssregistry.xml
ityou/bluetheme/profiles/default/ityou.bluetheme_various.txt
ityou/bluetheme/profiles/default/jsregistry.xml
ityou/bluetheme/profiles/default/metadata.xml
ityou/bluetheme/profiles/default/skins.xml
ityou/bluetheme/profiles/default/viewlets.xml
ityou/bluetheme/profiles/uninstall/skins.xml
ityou/bluetheme/profiles/uninstall/viewlets.xml
ityou/bluetheme/skins/ityou_bluetheme_images/CONTENT.txt
ityou/bluetheme/skins/ityou_bluetheme_images/link_icon.png
ityou/bluetheme/skins/ityou_bluetheme_images/logo.png
ityou/bluetheme/skins/ityou_bluetheme_styles/CONTENT.txt
