Metadata-Version: 1.0
Name: ityou.bluetheme
Version: 0.1
Summary: An installable theme for Plone 4
Home-page: http://www.ityou.de/
Author: Luc Muller
Author-email: lmuller@ityou.de
License: GPL
Keywords: plone zope theme ityou bluetheme
Platform: UNKNOWN
Classifier: Framework :: Plone
Classifier: Programming Language :: Python
